onnxruntime/__init__.py
onnxruntime/Privacy.md
onnxruntime/LICENSE
onnxruntime/ThirdPartyNotices.txt
onnxruntime/capi/__init__.py
onnxruntime/capi/onnxruntime_pybind11_state.cpython-37m-x86_64-linux-gnu.so
onnxruntime/capi/_ld_preload.py
onnxruntime/capi/onnxruntime_validation.py
onnxruntime/capi/onnxruntime_inference_collection.py
onnxruntime/capi/_pybind_state.py
onnxruntime/capi/training/__init__.py
onnxruntime/tools/__init__.py
onnxruntime/tools/symbolic_shape_infer.py
onnxruntime/tools/onnxruntime_test.py
onnxruntime/transformers/huggingface_models.py
onnxruntime/transformers/convert_tf_models_to_pytorch.py
onnxruntime/transformers/fusion_gelu_approximation.py
onnxruntime/transformers/fusion_embedlayer.py
onnxruntime/transformers/benchmark_gpt2.py
onnxruntime/transformers/machine_info.py
onnxruntime/transformers/gpt2_helper.py
onnxruntime/transformers/fusion_gpt_attention_no_past.py
onnxruntime/transformers/__init__.py
onnxruntime/transformers/fusion_reshape.py
onnxruntime/transformers/onnx_model.py
onnxruntime/transformers/fusion_base.py
onnxruntime/transformers/shape_optimizer.py
onnxruntime/transformers/bert_perf_test.py
onnxruntime/transformers/onnx_model_bert_keras.py
onnxruntime/transformers/parity_check_helper.py
onnxruntime/transformers/onnx_model_bert_tf.py
onnxruntime/transformers/gpt2_tester.py
onnxruntime/transformers/fusion_gpt_attention.py
onnxruntime/transformers/fusion_attention.py
onnxruntime/transformers/onnx_exporter.py
onnxruntime/transformers/bert_test_data.py
onnxruntime/transformers/fusion_utils.py
onnxruntime/transformers/benchmark_helper.py
onnxruntime/transformers/fusion_biasgelu.py
onnxruntime/transformers/fusion_gelu.py
onnxruntime/transformers/convert_to_onnx.py
onnxruntime/transformers/profiler.py
onnxruntime/transformers/fusion_layernorm.py
onnxruntime/transformers/fusion_skiplayernorm.py
onnxruntime/transformers/fusion_fastgelu.py
onnxruntime/transformers/optimizer.py
onnxruntime_openmp-1.7.0.dist-info/WHEEL
onnxruntime_openmp-1.7.0.dist-info/METADATA
onnxruntime_openmp-1.7.0.dist-info/RECORD
onnxruntime_openmp-1.7.0.dist-info/entry_points.txt
onnxruntime_openmp-1.7.0.dist-info/top_level.txt
